tormor/__init__.py
tormor/commands.py
tormor/connections.py
tormor/dsn.py
tormor/exceptions.py
tormor/main_script.py
tormor/path_helper.py
tormor/tests/__init__.py
tormor/tests/bootstrap.sh
tormor/tests/cleanup.sh
tormor/tests/script_file.txt
tormor/tests/script_file_dry.txt
tormor/tests/test_connections.py
tormor/tests/test_dsn.py
tormor/tests/test_path.py
tormor/tests/test_run_script.py
tormor/tests/Schema/customer/01_customer.sql
tormor/tests/Schema/customer/03_customer.sql
tormor/tests/Schema/employee/01_employee.sql
tormor/tests/Schema/product/01_product.sql
tormor/tests/Schema2/customer/02_customer.sql
tormor/tests/Schema2/department/01_department.sql
tormor-2.5.dist-info/entry_points.txt
tormor-2.5.dist-info/LICENSE
tormor-2.5.dist-info/WHEEL
tormor-2.5.dist-info/METADATA
tormor-2.5.dist-info/RECORD
