Metadata-Version: 2.1
Name: tormor
Version: 2.5
Summary: Database migration helper
Home-page: https://github.com/Proteus-tech/tormor
License: UNKNOWN
Author: Tle Ekkul
Author-email: e.aryuth@gmail.com
Requires-Python: ~=3.6
Classifier: License :: OSI Approved :: MIT License
Requires-Dist: asyncpg==0.18.3
Requires-Dist: click==7.0
Requires-Dist: coverage==4.5.1; extra == "test"
Requires-Dist: pytest==3.6.3; extra == "test"
Provides-Extra: test
